nested_property/__init__.py
nested_property-1.0.2.dist-info/licenses/LICENSE
nested_property-1.0.2.dist-info/METADATA
nested_property-1.0.2.dist-info/WHEEL
nested_property-1.0.2.dist-info/top_level.txt
nested_property-1.0.2.dist-info/RECORD
