Metadata-Version: 2.4
Name: nested-property
Version: 1.0.2
Summary: A python based library inspired by nested-property module in javascript
Home-page: https://github.com/giesekow/nested-property
Author: Giles Tetteh
Author-email: giles.ekow.tetteh@gmail.com
Keywords: nested-property,dict-property
Classifier: Programming Language :: Python :: 3
Classifier: License :: OSI Approved :: MIT License
Classifier: Operating System :: OS Independent
License-File: LICENSE
Dynamic: license-file
